yt_finder/__init__.py
yt_finder/result.py
yt_finder-1.1.0.dist-info/LICENSE
yt_finder-1.1.0.dist-info/METADATA
yt_finder-1.1.0.dist-info/WHEEL
yt_finder-1.1.0.dist-info/top_level.txt
yt_finder-1.1.0.dist-info/RECORD
