Metadata-Version: 2.1
Name: yt-finder
Version: 1.1.0
Summary: Perform YouTube video searches without the API. Fork of the youtube-search library.
Home-page: https://github.com/Weever1337/yt-finder
Author: NixxO (nixxoq), Weever (weever1337), Joe Tatusko (original author)
Author-email: weever1337@gmail.com
License: MIT
Classifier: License :: OSI Approved :: MIT License
Classifier: Programming Language :: Python :: 3
Classifier: Programming Language :: Python :: 3.8
Classifier: Programming Language :: Python :: 3.9
Classifier: Programming Language :: Python :: 3.10
Classifier: Programming Language :: Python :: 3.11
Classifier: Programming Language :: Python :: 3.12
License-File: LICENSE
Requires-Dist: loguru
Requires-Dist: aiohttp
